fundom/__init__.py
fundom/core.py
fundom/maybe.py
fundom/model.py
fundom/pointfree/__init__.py
fundom/pointfree/bytes_utils.py
fundom/pointfree/dict_utils.py
fundom/pointfree/str_utils.py
fundom/predicate.py
fundom/result.py
fundom-0.1.0.dist-info/WHEEL
fundom-0.1.0.dist-info/METADATA
fundom-0.1.0.dist-info/RECORD
