Metadata-Version: 2.1
Name: fundom
Version: 0.1.0
Summary: Common simple python monads for more readable and maintainable pipeline-based code.
License: MIT
Author: Ilya Katun
Author-email: katun.ilya@gmail.com
Requires-Python: >=3.10,<4.0
Classifier: License :: OSI Approved :: MIT License
Classifier: Programming Language :: Python :: 3
Classifier: Programming Language :: Python :: 3.10
